rpa_framework/__init__.py
rpa_framework-0.0.0.0.1.dist-info/WHEEL
rpa_framework-0.0.0.0.1.dist-info/METADATA
rpa_framework-0.0.0.0.1.dist-info/RECORD
