Metadata-Version: 2.1
Name: rpa-framework
Version: 0.0.0.0.1
Summary: Deprecated project. Current project is rpaframework.
Author: RPA Framework
Author-email: rpafw@robocorp.com
Requires-Python: >=3.7,<4.0
Classifier: Programming Language :: Python :: 3
Classifier: Programming Language :: Python :: 3.7
Classifier: Programming Language :: Python :: 3.8
